ponywhoosh/__init__.py
ponywhoosh/core.py
ponywhoosh/index.py
ponywhoosh/utils.py
ponywhoosh-1.7.8.dist-info/AUTHORS.rst
ponywhoosh-1.7.8.dist-info/LICENSE.md
ponywhoosh-1.7.8.dist-info/METADATA
ponywhoosh-1.7.8.dist-info/WHEEL
ponywhoosh-1.7.8.dist-info/top_level.txt
ponywhoosh-1.7.8.dist-info/RECORD
