Metadata-Version: 1.1
Name: ponywhoosh
Version: 1.7.8
Summary: Your database now searchable. The backend behind the Flask-PonyWhoosh.
Home-page: https://github.com/jonaprieto/ponywhoosh
Author: Jonathan Prieto-Cubides & Felipe Rodriguez
Author-email: jprieto9@eafit.edu.co
License: MIT
Keywords: elastic,engine,flask,flask-sqlalchemy,flask-whooshalchemy,mysql,pony,ponyorm,ponywhoosh,search,searchable,sqlite3,whoosh
Platform: any
Classifier: Environment :: Web Environment
Classifier: Intended Audience :: Developers
Classifier: License :: OSI Approved :: MIT License
Classifier: Operating System :: OS Independent
Classifier: Programming Language :: Python
Classifier: Topic :: Internet :: WWW/HTTP :: Dynamic Content
Classifier: Topic :: Software Development :: Libraries :: Python Modules
